timeawarepc/__init__.py
timeawarepc/find_cfc.py
timeawarepc/gc.py
timeawarepc/pcalg.py
timeawarepc/pcalg_helpers.py
timeawarepc/simulate_data.py
timeawarepc/tpc.py
timeawarepc/tpc_helpers.py
timeawarepc/tutorial.py
timeawarepc-1.2.4.dist-info/licenses/LICENSE
timeawarepc-1.2.4.dist-info/METADATA
timeawarepc-1.2.4.dist-info/WHEEL
timeawarepc-1.2.4.dist-info/top_level.txt
timeawarepc-1.2.4.dist-info/RECORD
