Metadata-Version: 2.4
Name: timeawarepc
Version: 1.2.4
Summary: Time-Aware PC Python Package
Home-page: https://github.com/biswasr/TimeAwarePC
Author: Rahul Biswas
Author-email: rahul.biswas@ucsf.edu
License: MIT
Classifier: Programming Language :: Python :: 3
Classifier: License :: OSI Approved :: MIT License
Classifier: Operating System :: OS Independent
Classifier: Programming Language :: Python :: 3.10
Requires-Python: >=3.7, <3.11
License-File: LICENSE
Requires-Dist: numpy
Requires-Dist: pandas
Requires-Dist: rpy2==3.5.11
Requires-Dist: networkx
Requires-Dist: scipy
Dynamic: author
Dynamic: author-email
Dynamic: classifier
Dynamic: description
Dynamic: description-content-type
Dynamic: home-page
Dynamic: license
Dynamic: license-file
Dynamic: requires-dist
Dynamic: requires-python
Dynamic: summary
